capybara_forms/__init__.py
capybara_forms/admin.py
capybara_forms/defines.py
capybara_forms/forms.py
capybara_forms/models.py
capybara_forms/utils.py
capybara_forms/widgets.py
capybara_forms/migrations/0001_initial.py
capybara_forms/migrations/__init__.py
capybara_forms/renderers/__init__.py
capybara_forms/renderers/filter.py
capybara_forms/renderers/form.py
capybara_forms/renderers/options.py
capybara_forms/static/capybara_forms/css/cpb_forms.css
capybara_forms/static/capybara_forms/css/cpb_forms.styl
capybara_forms/static/capybara_forms/css/jsoneditor.min.css
capybara_forms/static/capybara_forms/css/img/color_check.svg
capybara_forms/static/capybara_forms/css/img/jsoneditor-icons.svg
capybara_forms/static/capybara_forms/js/jquery-3.3.1.min.js
capybara_forms/static/capybara_forms/js/jsoneditor.min.js
capybara_forms/static/capybara_forms/js/parsley.min.js
capybara_forms/templates/capybara_forms/jsoneditor.html
capybara_forms/templates/capybara_forms/filter/checkbox.html
capybara_forms/templates/capybara_forms/filter/number.html
capybara_forms/templates/capybara_forms/filter/number_select.html
capybara_forms/templates/capybara_forms/filter/select.html
capybara_forms/templates/capybara_forms/filter/string.html
capybara_forms/templates/capybara_forms/form/checkbox.html
capybara_forms/templates/capybara_forms/form/color.html
capybara_forms/templates/capybara_forms/form/number.html
capybara_forms/templates/capybara_forms/form/select.html
capybara_forms/templates/capybara_forms/form/string.html
capybara_forms/templates/capybara_forms/parts/js_register_nested_select.html
capybara_forms-0.0.2.dist-info/LICENSE
capybara_forms-0.0.2.dist-info/METADATA
capybara_forms-0.0.2.dist-info/WHEEL
capybara_forms-0.0.2.dist-info/top_level.txt
capybara_forms-0.0.2.dist-info/RECORD
