Metadata-Version: 2.1
Name: capybara-forms
Version: 0.0.2
Summary: Dynamic Django forms and filters using JSON schema
Home-page: https://github.com/kenny1992/capybara_forms
Author: kenny1992
Author-email: apolevki09@gmail.com
License: UNKNOWN
Platform: UNKNOWN
Classifier: Programming Language :: Python
Classifier: Programming Language :: Python :: 3
Classifier: Framework :: Django
Classifier: Topic :: Internet :: WWW/HTTP
Classifier: Topic :: Internet :: WWW/HTTP :: Dynamic Content
Classifier: Topic :: Software Development :: Libraries :: Python Modules
Classifier: License :: OSI Approved :: MIT License
Requires-Dist: Django
